ftrack_utils/__init__.py
ftrack_utils/decorators/__init__.py
ftrack_utils/decorators/asynchronous.py
ftrack_utils/decorators/session.py
ftrack_utils/decorators/threading.py
ftrack_utils/decorators/track_usage.py
ftrack_utils/directories/__init__.py
ftrack_utils/directories/scan_dir.py
ftrack_utils/event_hub/__init__.py
ftrack_utils/event_hub/event_hub_thread.py
ftrack_utils/extensions/__init__.py
ftrack_utils/extensions/environment.py
ftrack_utils/extensions/overrides.py
ftrack_utils/extensions/registry.py
ftrack_utils/framework/__init__.py
ftrack_utils/framework/config/__init__.py
ftrack_utils/framework/config/tool.py
ftrack_utils/framework/remote.py
ftrack_utils/json/__init__.py
ftrack_utils/modules/__init__.py
ftrack_utils/modules/scan_modules.py
ftrack_utils/paths/__init__.py
ftrack_utils/process/__init__.py
ftrack_utils/process/monitor.py
ftrack_utils/rpc/__init__.py
ftrack_utils/rpc/js_rpc.py
ftrack_utils/server/__init__.py
ftrack_utils/server/send_event.py
ftrack_utils/server/track_usage.py
ftrack_utils/session/__init__.py
ftrack_utils/session/ftrack_api_session.py
ftrack_utils/string/__init__.py
ftrack_utils/threading/__init__.py
ftrack_utils/usage/__init__.py
ftrack_utils/usage/track_usage.py
ftrack_utils/version/__init__.py
ftrack_utils-3.1.4.dist-info/LICENSE.txt
ftrack_utils-3.1.4.dist-info/METADATA
ftrack_utils-3.1.4.dist-info/WHEEL
ftrack_utils-3.1.4.dist-info/RECORD
