Metadata-Version: 2.1
Name: ftrack-utils
Version: 3.1.4
Summary: ftrack utils library
Home-page: https://ftrack.com
License: Apache-2.0
Author: ftrack Integrations Team
Author-email: integrations@backlight.co
Requires-Python: >=3.7,<3.12
Classifier: License :: OSI Approved :: Apache Software License
Classifier: Programming Language :: Python :: 3
Classifier: Programming Language :: Python :: 3.7
Classifier: Programming Language :: Python :: 3.8
Classifier: Programming Language :: Python :: 3.9
Classifier: Programming Language :: Python :: 3.10
Classifier: Programming Language :: Python :: 3.11
Requires-Dist: clique (==1.6.1)
Requires-Dist: ftrack-python-api (>=2.5.4,<3.0.0)
Requires-Dist: six (>=1,<2)
Requires-Dist: toml (>=0.10.2,<0.11.0)
Project-URL: Repository, https://github.com/ftrackhq/integrations/tree/main/libs/utils
